quant_analytics_torch/__init__.py
quant_analytics_torch/analytics/__init__.py
quant_analytics_torch/calculators/__init__.py
quant_analytics_torch/calculators/deeplearningconditionalexpectation.py
quant_analytics_torch/calculators/deeplearninghedgingengine.py
quant_analytics_torch/calculators/pathgenerator.py
quant_analytics_torch/calculators/pathgeneratorlognormal.py
quant_analytics_torch/calculators/pathgeneratornormal.py
quant_analytics_torch/modules/__init__.py
quant_analytics_torch/modules/baseneuralnetworkmodule.py
quant_analytics_torch/modules/longshorttermmemory.py
quant_analytics_torch/sandbox/__init__.py
quant_analytics_torch/sandbox/multi_step_bachelier_classes.py
quant_analytics_torch/sandbox/one_step_bachelier.py
quant_analytics_torch/sandbox/test.py
quant_analytics_torch-0.0.3.dist-info/LICENSE
quant_analytics_torch-0.0.3.dist-info/METADATA
quant_analytics_torch-0.0.3.dist-info/WHEEL
quant_analytics_torch-0.0.3.dist-info/top_level.txt
quant_analytics_torch-0.0.3.dist-info/RECORD
