Metadata-Version: 2.1
Name: quant-analytics-torch
Version: 0.0.3
Summary: Quantitative analytics package based on PyTorch for deep learning of derivative pricing
Home-page: UNKNOWN
Author: UNKNOWN
Author-email: quant.analytics.torch@gmail.com
License: MIT License
Platform: UNKNOWN
